data_transfer_cli/.env
data_transfer_cli/__init__.py
data_transfer_cli/conf/cli.cfg
data_transfer_cli/dtcli.cfg
data_transfer_cli/dtcli.py
data_transfer_cli/dtproxy.py
data_transfer_cli/parser/__init__.py
data_transfer_cli/parser/cli_parser.py
data_transfer_cli-0.3.9.dist-info/METADATA
data_transfer_cli-0.3.9.dist-info/WHEEL
data_transfer_cli-0.3.9.dist-info/entry_points.txt
data_transfer_cli-0.3.9.dist-info/RECORD
