Metadata-Version: 2.3
Name: data-transfer-cli
Version: 0.3.9
Summary: HiDALGO Data Transfer CLI provides commands to transfer data between different data providers and consumers using NIFI pipelines
License: APL-2.0
Author: Jesús Gorroñogoitia
Author-email: jesus.gorronogoitia@eviden.com
Requires-Python: >=3.11, <4.0
Classifier: License :: Other/Proprietary License
Classifier: Programming Language :: Python :: 3
Classifier: Programming Language :: Python :: 3.11
Classifier: Programming Language :: Python :: 3.12
Classifier: Programming Language :: Python :: 3.13
Requires-Dist: hid_data_transfer_lib (>=0.3.9)
Requires-Dist: paramiko (>=3.3.1)
Requires-Dist: pyyaml (>=6.0.2,<7.0.0)
Requires-Dist: requests (>=2.31.0)
